MagmaPEC/Kd_calculation.py
MagmaPEC/PEC_configuration.py
MagmaPEC/__init__.py
MagmaPEC/equilibration_functions.py
MagmaPEC/plots.py
MagmaPEC/tools.py
MagmaPEC/PEC_model/PEC_model.py
MagmaPEC/PEC_model/__init__.py
MagmaPEC/PEC_model/scalar/Crystallisation_correction_scalar.py
MagmaPEC/PEC_model/scalar/Equilibration_scalar.py
MagmaPEC/PEC_model/scalar/__init__.py
MagmaPEC/PEC_model/vector/__init__.py
MagmaPEC/PEC_model/vector/crystallisation_correction_vector.py
MagmaPEC/PEC_model/vector/equilibration_vector.py
MagmaPEC/error_propagation/FeOi_error_propagation.py
MagmaPEC/error_propagation/MC_parameters.py
MagmaPEC/error_propagation/__init__.py
MagmaPEC/error_propagation/pec_MC_model.py
magmapec-1.0.6.dist-info/licenses/LICENSE
magmapec-1.0.6.dist-info/METADATA
magmapec-1.0.6.dist-info/WHEEL
magmapec-1.0.6.dist-info/top_level.txt
magmapec-1.0.6.dist-info/RECORD
