Metadata-Version: 2.4
Name: MagmaPEC
Version: 1.0.6
Summary: MagmaPandas based PEC correction tool for olivine-hosted melt inclusions.
Author: Thomas van Gerve
License: MIT License
Project-URL: Homepage, https://github.com/TDGerve/MagmaPEC
Classifier: Programming Language :: Python :: 3
Classifier: License :: OSI Approved :: MIT License
Classifier: Operating System :: OS Independent
Requires-Python: >=3.10
License-File: LICENSE
Requires-Dist: pandas<=2.1.4
Requires-Dist: numpy<=1.26.4
Requires-Dist: scipy
Requires-Dist: alive_progress
Requires-Dist: matplotlib-label-lines
Requires-Dist: matplotlib
Requires-Dist: elementMass>=1.1.0
Requires-Dist: magmapandas>=2.2.3
Requires-Dist: ipython
Requires-Dist: scikit-learn
Requires-Dist: statsmodels
Dynamic: license-file
